Workbook

Sheet Settings
A1: Company Settings
A3: Company Name | B3: Flash Lighting Services Ltd
A4: VAT Rate (%) | B4: 15
A5: Financial Year Start | B5: 2025-01-01
A7: Opening Balances
A8: Cash in Hand (Opening) | B8: 5000
A9: Cash at Bank (Opening) | B9: 50000
A11: Expense Categories | D11: Payment Methods
A12: Equipment Purchase | D12: Cash
A13: Equipment Maintenance | D13: Bank Transfer
A14: Transport/Fuel | D14: Cheque
A15: Salaries/Wages | D15: Mobile Money
A16: Rent | D16: Card
A17: Utilities
A18: Insurance
A19: Marketing
A20: Office Supplies
A21: Professional Fees
A22: Bank Charges
A23: Other

Sheet Invoices
A1: Invoice No. | B1: Date | C1: Client Name | D1: Event Date | E1: Items/Equipment | F1: Quantity | G1: Unit Price | H1: Subtotal | I1: VAT Rate | J1: VAT Amount | K1: Total Amount | L1: Amount Received | M1: Balance
A2: INV-2025-001 | B2: 45672 | C2: Sample Client Ltd | D2: 45677 | E2: LED Stage Lights x10, Sound System | F2: 1 | G2: 15000 | H2: =F2*G2 | I2: =Settings!$B$4/100 | J2: =H2*I2 | K2: =H2+J2 | L2: 15000 | M2: =K2-L2

Sheet Revenue
A1: Date | B1: Invoice No. | C1: Client Name | D1: Service/Equipment Provided | E1: Quantity | F1: Unit Price | G1: Total Amount | H1: Amount Received | I1: Balance | K1: REVENUE SUMMARY
A2: =Invoices!B2 | B2: =Invoices!A2 | C2: =Invoices!C2 | D2: =Invoices!E2 | E2: =Invoices!F2 | F2: =Invoices!G2 | G2: =Invoices!K2 | H2: =Invoices!L2 | I2: =Invoices!M2
K3: Today's Revenue | L3: =SUMIFS(H:H,A:A,TODAY())
K4: This Month's Revenue | L4: =SUMIFS(H:H,A:A,">="&DATE(YEAR(TODAY()),MONTH(TODAY()),1),A:A,"<"&DATE(YEAR(TODAY()),MONTH(TODAY())+1,1))
K5: This Year's Revenue | L5: =SUMIFS(H:H,A:A,">="&DATE(YEAR(TODAY()),1,1),A:A,"<"&DATE(YEAR(TODAY())+1,1,1))
K7: Total Outstanding | L7: =SUM(I:I)

Sheet Expenses
A1: Date | B1: Expense Category | C1: Vendor | D1: Description | E1: Amount | F1: Payment Method | G1: Reference | I1: EXPENSE SUMMARY
A2: 45667 | B2: Equipment Purchase | C2: Tech Supplies Ltd | D2: 10x LED Par Lights | E2: 25000 | F2: Bank Transfer | G2: TXN-001
I3: This Month's Expenses | J3: =SUMIFS(E:E,A:A,">="&DATE(YEAR(TODAY()),MONTH(TODAY()),1),A:A,"<"&DATE(YEAR(TODAY()),MONTH(TODAY())+1,1))
I4: This Year's Expenses | J4: =SUMIFS(E:E,A:A,">="&DATE(YEAR(TODAY()),1,1),A:A,"<"&DATE(YEAR(TODAY())+1,1,1))
I6: By Category (YTD)
I7: Equipment Purchase | J7: =SUMIFS(E:E,B:B,I7,A:A,">="&DATE(YEAR(TODAY()),1,1))
I8: Equipment Maintenance | J8: =SUMIFS(E:E,B:B,I8,A:A,">="&DATE(YEAR(TODAY()),1,1))
I9: Transport/Fuel | J9: =SUMIFS(E:E,B:B,I9,A:A,">="&DATE(YEAR(TODAY()),1,1))
I10: Salaries/Wages | J10: =SUMIFS(E:E,B:B,I10,A:A,">="&DATE(YEAR(TODAY()),1,1))
I11: Rent | J11: =SUMIFS(E:E,B:B,I11,A:A,">="&DATE(YEAR(TODAY()),1,1))
I12: Utilities | J12: =SUMIFS(E:E,B:B,I12,A:A,">="&DATE(YEAR(TODAY()),1,1))
I13: Insurance | J13: =SUMIFS(E:E,B:B,I13,A:A,">="&DATE(YEAR(TODAY()),1,1))
I14: Marketing | J14: =SUMIFS(E:E,B:B,I14,A:A,">="&DATE(YEAR(TODAY()),1,1))
I15: Office Supplies | J15: =SUMIFS(E:E,B:B,I15,A:A,">="&DATE(YEAR(TODAY()),1,1))
I16: Professional Fees | J16: =SUMIFS(E:E,B:B,I16,A:A,">="&DATE(YEAR(TODAY()),1,1))
I17: Bank Charges | J17: =SUMIFS(E:E,B:B,I17,A:A,">="&DATE(YEAR(TODAY()),1,1))
I18: Other | J18: =SUMIFS(E:E,B:B,I18,A:A,">="&DATE(YEAR(TODAY()),1,1))

Sheet Inventory
A1: Stock ID | B1: Item Description | C1: Unit Price | D1: Quantity in Store | E1: Quantity Rented Out | F1: Stock in Transit | G1: Total Quantity | H1: Total Stock Value
A2: STK-001 | B2: LED Par Light | C2: 2500 | D2: 20 | E2: 5 | F2: 0 | G2: =D2+E2+F2 | H2: =C2*G2
A3: STK-002 | B3: Moving Head Light | C3: 8000 | D3: 10 | E3: 3 | F3: 2 | G3: =D3+E3+F3 | H3: =C3*G3 | J3: Available for Rent | K3: =SUM(D:D)
A4: STK-003 | B4: Sound System (Complete) | C4: 45000 | D4: 3 | E4: 1 | F4: 0 | G4: =D4+E4+F4 | H4: =C4*G4 | J4: Currently Rented | K4: =SUM(E:E)
A5: STK-004 | B5: Smoke Machine | C5: 3500 | D5: 8 | E5: 2 | F5: 0 | G5: =D5+E5+F5 | H5: =C5*G5 | J5: In Transit | K5: =SUM(F:F)
A6: STK-005 | B6: DMX Controller | C6: 5000 | D6: 5 | E6: 1 | F6: 0 | G6: =D6+E6+F6 | H6: =C6*G6
A7: STK-006 | B7: Lighting Truss (per meter) | C7: 800 | D7: 50 | E7: 20 | F7: 0 | G7: =D7+E7+F7 | H7: =C7*G7
A8: STK-007 | B8: Power Distribution Box | C8: 1200 | D8: 15 | E8: 5 | F8: 0 | G8: =D8+E8+F8 | H8: =C8*G8
A9: STK-008 | B9: Microphone (Wireless) | C9: 1500 | D9: 12 | E9: 4 | F9: 0 | G9: =D9+E9+F9 | H9: =C9*G9
A10: STK-009 | B10: Speaker (500W) | C10: 6000 | D10: 8 | E10: 3 | F10: 1 | G10: =D10+E10+F10 | H10: =C10*G10
A11: STK-010 | B11: Cable Set (Complete) | C11: 300 | D11: 30 | E11: 10 | F11: 5 | G11: =D11+E11+F11 | H11: =C11*G11
A12: TOTAL STOCK VALUE | H12: =SUM(H2:H11)

Sheet Trade Debtors
A1: Invoice No. | B1: Date | C1: Client Name | D1: Amount Owed | E1: Due Date | F1: Days Outstanding | G1: Status
A2: This sheet auto-populates from Invoices where Balance > 0
I3: Total Outstanding | J3: =SUM(D:D)
A4: =IFERROR(INDEX(Invoices!$A:$A,SMALL(IF(Invoices!$M$2:$M$1000>0,ROW(Invoices!$M$2:$M$1000)),ROW()-3)),"") | B4: =IFERROR(INDEX(Invoices!$B:$B,MATCH(A4,Invoices!$A:$A,0)),"") | C4: =IFERROR(INDEX(Invoices!$C:$C,MATCH(A4,Invoices!$A:$A,0)),"") | D4: =IFERROR(INDEX(Invoices!$M:$M,MATCH(A4,Invoices!$A:$A,0)),"") | E4: =IFERROR(B4+30,"") | F4: =IFERROR(IF(A4<>"",TODAY()-B4,""),"") | G4: =IFERROR(IF(F4="","",IF(F4>60,"Overdue",IF(F4>30,"Due Soon","Current"))),"")
I5: Current (0-30 days) | J5: =SUMIF(G:G,"Current",D:D)
I6: Due Soon (31-60 days) | J6: =SUMIF(G:G,"Due Soon",D:D)
I7: Overdue (>60 days) | J7: =SUMIF(G:G,"Overdue",D:D)

Sheet Cash Position
A1: CASH POSITION STATEMENT
A2: As at: 2025-11-22
A4: CASH IN HAND | D4: MONTHLY CASH FLOW
A5: Opening Balance | B5: =Settings!B8 | D5: Month | E5: Inflows | F5: Outflows | G5: Net
A6: Cash Received (YTD) | B6: =SUMIFS(Revenue!H:H,Revenue!A:A,">="&Settings!$B$5,Expenses!F:F,"Cash") | D6: January | E6: =SUMIFS(Revenue!H:H,Revenue!A:A,">="&DATE(YEAR(TODAY()),1,1),Revenue!A:A,"<"&DATE(YEAR(TODAY()),1+1,1)) | F6: =SUMIFS(Expenses!E:E,Expenses!A:A,">="&DATE(YEAR(TODAY()),1,1),Expenses!A:A,"<"&DATE(YEAR(TODAY()),1+1,1)) | G6: =E6-F6
A7: Cash Paid (YTD) | B7: =SUMIFS(Expenses!E:E,Expenses!A:A,">="&Settings!$B$5,Expenses!F:F,"Cash") | D7: February | E7: =SUMIFS(Revenue!H:H,Revenue!A:A,">="&DATE(YEAR(TODAY()),2,1),Revenue!A:A,"<"&DATE(YEAR(TODAY()),2+1,1)) | F7: =SUMIFS(Expenses!E:E,Expenses!A:A,">="&DATE(YEAR(TODAY()),2,1),Expenses!A:A,"<"&DATE(YEAR(TODAY()),2+1,1)) | G7: =E7-F7
A8: Closing Cash in Hand | B8: =B5+B6-B7 | D8: March | E8: =SUMIFS(Revenue!H:H,Revenue!A:A,">="&DATE(YEAR(TODAY()),3,1),Revenue!A:A,"<"&DATE(YEAR(TODAY()),3+1,1)) | F8: =SUMIFS(Expenses!E:E,Expenses!A:A,">="&DATE(YEAR(TODAY()),3,1),Expenses!A:A,"<"&DATE(YEAR(TODAY()),3+1,1)) | G8: =E8-F8
D9: April | E9: =SUMIFS(Revenue!H:H,Revenue!A:A,">="&DATE(YEAR(TODAY()),4,1),Revenue!A:A,"<"&DATE(YEAR(TODAY()),4+1,1)) | F9: =SUMIFS(Expenses!E:E,Expenses!A:A,">="&DATE(YEAR(TODAY()),4,1),Expenses!A:A,"<"&DATE(YEAR(TODAY()),4+1,1)) | G9: =E9-F9
A10: CASH AT BANK | D10: May | E10: =SUMIFS(Revenue!H:H,Revenue!A:A,">="&DATE(YEAR(TODAY()),5,1),Revenue!A:A,"<"&DATE(YEAR(TODAY()),5+1,1)) | F10: =SUMIFS(Expenses!E:E,Expenses!A:A,">="&DATE(YEAR(TODAY()),5,1),Expenses!A:A,"<"&DATE(YEAR(TODAY()),5+1,1)) | G10: =E10-F10
A11: Opening Balance | B11: =Settings!B9 | D11: June | E11: =SUMIFS(Revenue!H:H,Revenue!A:A,">="&DATE(YEAR(TODAY()),6,1),Revenue!A:A,"<"&DATE(YEAR(TODAY()),6+1,1)) | F11: =SUMIFS(Expenses!E:E,Expenses!A:A,">="&DATE(YEAR(TODAY()),6,1),Expenses!A:A,"<"&DATE(YEAR(TODAY()),6+1,1)) | G11: =E11-F11
A12: Bank Receipts (YTD) | B12: =SUMIFS(Revenue!H:H,Revenue!A:A,">="&Settings!$B$5)-B6 | D12: July | E12: =SUMIFS(Revenue!H:H,Revenue!A:A,">="&DATE(YEAR(TODAY()),7,1),Revenue!A:A,"<"&DATE(YEAR(TODAY()),7+1,1)) | F12: =SUMIFS(Expenses!E:E,Expenses!A:A,">="&DATE(YEAR(TODAY()),7,1),Expenses!A:A,"<"&DATE(YEAR(TODAY()),7+1,1)) | G12: =E12-F12
A13: Bank Payments (YTD) | B13: =SUMIFS(Expenses!E:E,Expenses!A:A,">="&Settings!$B$5)-B7 | D13: August | E13: =SUMIFS(Revenue!H:H,Revenue!A:A,">="&DATE(YEAR(TODAY()),8,1),Revenue!A:A,"<"&DATE(YEAR(TODAY()),8+1,1)) | F13: =SUMIFS(Expenses!E:E,Expenses!A:A,">="&DATE(YEAR(TODAY()),8,1),Expenses!A:A,"<"&DATE(YEAR(TODAY()),8+1,1)) | G13: =E13-F13
A14: Closing Cash at Bank | B14: =B11+B12-B13 | D14: September | E14: =SUMIFS(Revenue!H:H,Revenue!A:A,">="&DATE(YEAR(TODAY()),9,1),Revenue!A:A,"<"&DATE(YEAR(TODAY()),9+1,1)) | F14: =SUMIFS(Expenses!E:E,Expenses!A:A,">="&DATE(YEAR(TODAY()),9,1),Expenses!A:A,"<"&DATE(YEAR(TODAY()),9+1,1)) | G14: =E14-F14
D15: October | E15: =SUMIFS(Revenue!H:H,Revenue!A:A,">="&DATE(YEAR(TODAY()),10,1),Revenue!A:A,"<"&DATE(YEAR(TODAY()),10+1,1)) | F15: =SUMIFS(Expenses!E:E,Expenses!A:A,">="&DATE(YEAR(TODAY()),10,1),Expenses!A:A,"<"&DATE(YEAR(TODAY()),10+1,1)) | G15: =E15-F15
A16: TOTAL CASH POSITION | B16: =B8+B14 | D16: November | E16: =SUMIFS(Revenue!H:H,Revenue!A:A,">="&DATE(YEAR(TODAY()),11,1),Revenue!A:A,"<"&DATE(YEAR(TODAY()),11+1,1)) | F16: =SUMIFS(Expenses!E:E,Expenses!A:A,">="&DATE(YEAR(TODAY()),11,1),Expenses!A:A,"<"&DATE(YEAR(TODAY()),11+1,1)) | G16: =E16-F16
D17: December | E17: =SUMIFS(Revenue!H:H,Revenue!A:A,">="&DATE(YEAR(TODAY()),12,1),Revenue!A:A,"<"&DATE(YEAR(TODAY()),12+1,1)) | F17: =SUMIFS(Expenses!E:E,Expenses!A:A,">="&DATE(YEAR(TODAY()),12,1),Expenses!A:A,"<"&DATE(YEAR(TODAY()),12+1,1)) | G17: =E17-F17

Sheet Tax Summary
A1: END-OF-YEAR TAX SUMMARY
A2: Financial Year: 2025
A4: REVENUE
A5: Total Revenue (Invoiced) | B5: =SUMIFS(Revenue!G:G,Revenue!A:A,">="&Settings!$B$5,Revenue!A:A,"<"&DATE(YEAR(Settings!$B$5)+1,1,1))
A6: Total Revenue (Received) | B6: =SUMIFS(Revenue!H:H,Revenue!A:A,">="&Settings!$B$5,Revenue!A:A,"<"&DATE(YEAR(Settings!$B$5)+1,1,1))
A7: Outstanding Receivables | B7: =B5-B6
A9: VALUE ADDED TAX (VAT)
A10: VAT Collected on Sales | B10: =SUMIFS(Invoices!J:J,Invoices!B:B,">="&Settings!$B$5,Invoices!B:B,"<"&DATE(YEAR(Settings!$B$5)+1,1,1))
A11: VAT Paid on Purchases | B11: =SUMIFS(Expenses!E:E,Expenses!A:A,">="&Settings!$B$5,Expenses!A:A,"<"&DATE(YEAR(Settings!$B$5)+1,1,1))*(Settings!$B$4/100)/(1+Settings!$B$4/100)
A12: Net VAT Payable | B12: =B10-B11
A14: EXPENSES (Deductible)
A15: Equipment Purchase | B15: =SUMIFS(Expenses!E:E,Expenses!B:B,A15,Expenses!A:A,">="&Settings!$B$5,Expenses!A:A,"<"&DATE(YEAR(Settings!$B$5)+1,1,1))
A16: Equipment Maintenance | B16: =SUMIFS(Expenses!E:E,Expenses!B:B,A16,Expenses!A:A,">="&Settings!$B$5,Expenses!A:A,"<"&DATE(YEAR(Settings!$B$5)+1,1,1))
A17: Transport/Fuel | B17: =SUMIFS(Expenses!E:E,Expenses!B:B,A17,Expenses!A:A,">="&Settings!$B$5,Expenses!A:A,"<"&DATE(YEAR(Settings!$B$5)+1,1,1))
A18: Salaries/Wages | B18: =SUMIFS(Expenses!E:E,Expenses!B:B,A18,Expenses!A:A,">="&Settings!$B$5,Expenses!A:A,"<"&DATE(YEAR(Settings!$B$5)+1,1,1))
A19: Rent | B19: =SUMIFS(Expenses!E:E,Expenses!B:B,A19,Expenses!A:A,">="&Settings!$B$5,Expenses!A:A,"<"&DATE(YEAR(Settings!$B$5)+1,1,1))
A20: Utilities | B20: =SUMIFS(Expenses!E:E,Expenses!B:B,A20,Expenses!A:A,">="&Settings!$B$5,Expenses!A:A,"<"&DATE(YEAR(Settings!$B$5)+1,1,1))
A21: Insurance | B21: =SUMIFS(Expenses!E:E,Expenses!B:B,A21,Expenses!A:A,">="&Settings!$B$5,Expenses!A:A,"<"&DATE(YEAR(Settings!$B$5)+1,1,1))
A22: Marketing | B22: =SUMIFS(Expenses!E:E,Expenses!B:B,A22,Expenses!A:A,">="&Settings!$B$5,Expenses!A:A,"<"&DATE(YEAR(Settings!$B$5)+1,1,1))
A23: Office Supplies | B23: =SUMIFS(Expenses!E:E,Expenses!B:B,A23,Expenses!A:A,">="&Settings!$B$5,Expenses!A:A,"<"&DATE(YEAR(Settings!$B$5)+1,1,1))
A24: Professional Fees | B24: =SUMIFS(Expenses!E:E,Expenses!B:B,A24,Expenses!A:A,">="&Settings!$B$5,Expenses!A:A,"<"&DATE(YEAR(Settings!$B$5)+1,1,1))
A25: Bank Charges | B25: =SUMIFS(Expenses!E:E,Expenses!B:B,A25,Expenses!A:A,">="&Settings!$B$5,Expenses!A:A,"<"&DATE(YEAR(Settings!$B$5)+1,1,1))
A26: Other | B26: =SUMIFS(Expenses!E:E,Expenses!B:B,A26,Expenses!A:A,">="&Settings!$B$5,Expenses!A:A,"<"&DATE(YEAR(Settings!$B$5)+1,1,1))
A27: Total Expenses | B27: =SUM(B15:B26)
A29: NET PROFIT BEFORE TAX | B29: =B6-B27
A30: Profit Margin (%) | B30: =IF(B6=0,0,B29/B6)

Sheet Dashboard
A1: BUSINESS HEALTH DASHBOARD
A2: Updated: 2025-11-22 13:07
A4: KEY FINANCIAL METRICS
A6: Monthly Revenue | B6: =Revenue!L4 | D6: Cash in Hand | E6: ='Cash Position'!B8
A7: Monthly Expenses | B7: =Expenses!J3 | D7: Cash at Bank | E7: ='Cash Position'!B14
A8: Monthly Net Profit | B8: =B6-B7 | D8: Total Cash | E8: =E6+E7
A9: Profit Margin | B9: =IF(B6=0,0,B8/B6)
D10: Outstanding Invoices | E10: ='Trade Debtors'!J3
A11: YTD Revenue | B11: =Revenue!L5 | D11: Total Stock Value | E11: =Inventory!H12
A12: YTD Expenses | B12: =Expenses!J4
A13: YTD Net Profit | B13: =B11-B12
A14: YTD Profit Margin | B14: =IF(B11=0,0,B13/B11)
A16: REVENUE VS EXPENSE TREND (Monthly)
A17: Month | B17: Revenue | C17: Expenses | D17: Net Profit
A18: January | B18: =SUMIFS(Revenue!H:H,Revenue!A:A,">="&DATE(YEAR(TODAY()),1,1),Revenue!A:A,"<"&DATE(YEAR(TODAY()),1+1,1)) | C18: =SUMIFS(Expenses!E:E,Expenses!A:A,">="&DATE(YEAR(TODAY()),1,1),Expenses!A:A,"<"&DATE(YEAR(TODAY()),1+1,1)) | D18: =B18-C18
A19: February | B19: =SUMIFS(Revenue!H:H,Revenue!A:A,">="&DATE(YEAR(TODAY()),2,1),Revenue!A:A,"<"&DATE(YEAR(TODAY()),2+1,1)) | C19: =SUMIFS(Expenses!E:E,Expenses!A:A,">="&DATE(YEAR(TODAY()),2,1),Expenses!A:A,"<"&DATE(YEAR(TODAY()),2+1,1)) | D19: =B19-C19
A20: March | B20: =SUMIFS(Revenue!H:H,Revenue!A:A,">="&DATE(YEAR(TODAY()),3,1),Revenue!A:A,"<"&DATE(YEAR(TODAY()),3+1,1)) | C20: =SUMIFS(Expenses!E:E,Expenses!A:A,">="&DATE(YEAR(TODAY()),3,1),Expenses!A:A,"<"&DATE(YEAR(TODAY()),3+1,1)) | D20: =B20-C20
A21: April | B21: =SUMIFS(Revenue!H:H,Revenue!A:A,">="&DATE(YEAR(TODAY()),4,1),Revenue!A:A,"<"&DATE(YEAR(TODAY()),4+1,1)) | C21: =SUMIFS(Expenses!E:E,Expenses!A:A,">="&DATE(YEAR(TODAY()),4,1),Expenses!A:A,"<"&DATE(YEAR(TODAY()),4+1,1)) | D21: =B21-C21
A22: May | B22: =SUMIFS(Revenue!H:H,Revenue!A:A,">="&DATE(YEAR(TODAY()),5,1),Revenue!A:A,"<"&DATE(YEAR(TODAY()),5+1,1)) | C22: =SUMIFS(Expenses!E:E,Expenses!A:A,">="&DATE(YEAR(TODAY()),5,1),Expenses!A:A,"<"&DATE(YEAR(TODAY()),5+1,1)) | D22: =B22-C22
A23: June | B23: =SUMIFS(Revenue!H:H,Revenue!A:A,">="&DATE(YEAR(TODAY()),6,1),Revenue!A:A,"<"&DATE(YEAR(TODAY()),6+1,1)) | C23: =SUMIFS(Expenses!E:E,Expenses!A:A,">="&DATE(YEAR(TODAY()),6,1),Expenses!A:A,"<"&DATE(YEAR(TODAY()),6+1,1)) | D23: =B23-C23
A24: July | B24: =SUMIFS(Revenue!H:H,Revenue!A:A,">="&DATE(YEAR(TODAY()),7,1),Revenue!A:A,"<"&DATE(YEAR(TODAY()),7+1,1)) | C24: =SUMIFS(Expenses!E:E,Expenses!A:A,">="&DATE(YEAR(TODAY()),7,1),Expenses!A:A,"<"&DATE(YEAR(TODAY()),7+1,1)) | D24: =B24-C24
A25: August | B25: =SUMIFS(Revenue!H:H,Revenue!A:A,">="&DATE(YEAR(TODAY()),8,1),Revenue!A:A,"<"&DATE(YEAR(TODAY()),8+1,1)) | C25: =SUMIFS(Expenses!E:E,Expenses!A:A,">="&DATE(YEAR(TODAY()),8,1),Expenses!A:A,"<"&DATE(YEAR(TODAY()),8+1,1)) | D25: =B25-C25
A26: September | B26: =SUMIFS(Revenue!H:H,Revenue!A:A,">="&DATE(YEAR(TODAY()),9,1),Revenue!A:A,"<"&DATE(YEAR(TODAY()),9+1,1)) | C26: =SUMIFS(Expenses!E:E,Expenses!A:A,">="&DATE(YEAR(TODAY()),9,1),Expenses!A:A,"<"&DATE(YEAR(TODAY()),9+1,1)) | D26: =B26-C26
A27: October | B27: =SUMIFS(Revenue!H:H,Revenue!A:A,">="&DATE(YEAR(TODAY()),10,1),Revenue!A:A,"<"&DATE(YEAR(TODAY()),10+1,1)) | C27: =SUMIFS(Expenses!E:E,Expenses!A:A,">="&DATE(YEAR(TODAY()),10,1),Expenses!A:A,"<"&DATE(YEAR(TODAY()),10+1,1)) | D27: =B27-C27
A28: November | B28: =SUMIFS(Revenue!H:H,Revenue!A:A,">="&DATE(YEAR(TODAY()),11,1),Revenue!A:A,"<"&DATE(YEAR(TODAY()),11+1,1)) | C28: =SUMIFS(Expenses!E:E,Expenses!A:A,">="&DATE(YEAR(TODAY()),11,1),Expenses!A:A,"<"&DATE(YEAR(TODAY()),11+1,1)) | D28: =B28-C28
A29: December | B29: =SUMIFS(Revenue!H:H,Revenue!A:A,">="&DATE(YEAR(TODAY()),12,1),Revenue!A:A,"<"&DATE(YEAR(TODAY()),12+1,1)) | C29: =SUMIFS(Expenses!E:E,Expenses!A:A,">="&DATE(YEAR(TODAY()),12,1),Expenses!A:A,"<"&DATE(YEAR(TODAY()),12+1,1)) | D29: =B29-C29
